hostedsms/__init__.py
hostedsms/api.py
hostedsms/exceptions.py
hostedsms/responses.py
hostedsms/settings.py
hostedsms_api-1.0.0.dist-info/LICENSE
hostedsms_api-1.0.0.dist-info/METADATA
hostedsms_api-1.0.0.dist-info/WHEEL
hostedsms_api-1.0.0.dist-info/RECORD
